MANIFEST.in
README.md
setup.py
ldap_notify/__init__.py
ldap_notify/algorithm.py
ldap_notify/config.py
ldap_notify/connection.py
ldap_notify/globals.py
ldap_notify/mail.py
ldap_notify/main.py
ldap_notify/utils.py
ldap_notify.egg-info/PKG-INFO
ldap_notify.egg-info/SOURCES.txt
ldap_notify.egg-info/dependency_links.txt
ldap_notify.egg-info/requires.txt
ldap_notify.egg-info/top_level.txt
ldap_notify/templates/admin.tmpl.txt
ldap_notify/templates/notify.tmpl.html
ldap_notify/templates/notify.tmpl.txt
scripts/ldap-notify