Metadata-Version: 1.0
Name: ldap-notify
Version: 0.8.3
Summary: LDAP Login/Password Email Notification Service
Home-page: https://github.com/sttts/ldap_notify
Author: Dr. Stefan Schimanski
Author-email: stefan.schimanski@gmail.com
License: GPL
Keywords: ldap notification eDirectory
Platform: UNKNOWN
Classifier: License :: OSI Approved :: GNU General Public License (GPL)
Classifier: Programming Language :: Python
Classifier: Development Status :: 4 - Beta
Classifier: Topic :: System :: Systems Administration :: Authentication/Directory :: LDAP
